ngfp/__init__.py
ngfp/active.py
ngfp/background.py
ngfp/board.py
ngfp/config.py
ngfp/dialog.py
ngfp/history.py
ngfp/labels.py
ngfp/marbles.py
ngfp/my_init.py
ngfp/ngfp.py
ngfp/randboard.py
ngfp/version.py
ngfp/png/arrows/picDDownW.png
ngfp/png/arrows/picDLeftW.png
ngfp/png/arrows/picDRightW.png
ngfp/png/arrows/picDUpW.png
ngfp/png/backgrounds/bbg.png
ngfp/png/backgrounds/gbg.png
ngfp/png/backgrounds/lgbg.png
ngfp/png/backgrounds/wbg.png
ngfp/png/colors/black.png
ngfp/png/colors/black_half.png
ngfp/png/colors/blue.png
ngfp/png/colors/blue_half.png
ngfp/png/colors/green.png
ngfp/png/colors/green_half.png
ngfp/png/colors/orange.png
ngfp/png/colors/orange_half.png
ngfp/png/colors/purple.png
ngfp/png/colors/purple_half.png
ngfp/png/colors/red.png
ngfp/png/colors/red_half.png
ngfp/png/colors/yellow.png
ngfp/png/colors/yellow_half.png
ngfp/png/controls/picIAbout.png
ngfp/png/controls/picICheck.png
ngfp/png/controls/picIFlipBoards.png
ngfp/png/controls/picINew.png
ngfp/png/controls/picIOpen.png
ngfp/png/controls/picISave.png
ngfp/png/marbles/black_marbles.png
ngfp/png/marbles/blue_marbles.png
ngfp/png/marbles/green_marbles.png
ngfp/png/marbles/purple_marbles.png
ngfp/png/marbles/red_marbles.png
ngfp/png/marbles/yellow_marbles.png
ngfp/png/markers/picMkCircle.png
ngfp/png/markers/picMkSquare.png
ngfp/png/markers/picMkTriangle.png
ngfp/png/markers/picMkVee.png
ngfp/png/mirrors/00_bg.png
ngfp/png/mirrors/01_normal.png
ngfp/png/mirrors/02_normal.png
ngfp/png/mirrors/03_flip2.png
ngfp/png/mirrors/04_flip2.png
ngfp/png/mirrors/05_flip4.png
ngfp/png/mirrors/06_flip4.png
ngfp/png/mirrors/07_flip4.png
ngfp/png/mirrors/08_flip4.png
ngfp/png/mirrors/09_block.png
ngfp/png/mirrors/10_sink.png
ngfp/png/mirrors/11_axial.png
ngfp/png/mirrors/12_axial.png
ngfp/png/mirrors/13_axial2.png
ngfp/png/mirrors/14_axial2.png
ngfp/png/mirrors/15_rotator.png
ngfp/png/mirrors/16_rotator.png
ngfp/png/mirrors/17_rotator2.png
ngfp/png/mirrors/18_rotator2.png
ngfp/png/mirrors/19_half.png
ngfp-0.2.6.dist-info/AUTHORS
ngfp-0.2.6.dist-info/LICENSE
ngfp-0.2.6.dist-info/LICENSE.GPL
ngfp-0.2.6.dist-info/METADATA
ngfp-0.2.6.dist-info/NOTICE
ngfp-0.2.6.dist-info/WHEEL
ngfp-0.2.6.dist-info/entry_points.txt
ngfp-0.2.6.dist-info/top_level.txt
ngfp-0.2.6.dist-info/RECORD
