Metadata-Version: 2.1
Name: ngfp
Version: 0.2.6
Summary: A puzzle game based upon gfpoken.
Home-page: https://https://github.com/flowerbug/ngfp
Author: Flowerbug
Author-email: flowerbug@anthive.com
License: Apache-2.0
Platform: UNKNOWN
Classifier: License :: OSI Approved :: Apache Software License
Classifier: License :: OSI Approved :: GNU General Public License v3 or later (GPLv3+)
Classifier: Programming Language :: Python :: 3
Classifier: Operating System :: POSIX :: Linux
Classifier: Intended Audience :: End Users/Desktop
Classifier: Topic :: Games/Entertainment :: Puzzle Games
Provides: ngfp
Requires-Python: >=3
Requires-Dist: pycairo
Requires-Dist: pyglet (>=1.3.0)
Requires-Dist: pygobject
